ishell/__init__.py
ishell/command.py
ishell/console.py
ishell/log.py
ishell/utils.py
ishell-0.1.8.dist-info/LICENSE.txt
ishell-0.1.8.dist-info/METADATA
ishell-0.1.8.dist-info/WHEEL
ishell-0.1.8.dist-info/top_level.txt
ishell-0.1.8.dist-info/RECORD
